fair/__init__.py
fair/cli.py
fair/common.py
fair/configuration/__init__.py
fair/configuration/validation.py
fair/exceptions.py
fair/files.txt
fair/history.py
fair/identifiers.py
fair/logging.py
fair/register.py
fair/registry/__init__.py
fair/registry/file_formats.json
fair/registry/file_types.py
fair/registry/requests.py
fair/registry/server.py
fair/registry/storage.py
fair/registry/sync.py
fair/registry/versioning.py
fair/run.py
fair/session.py
fair/staging.py
fair/templates/__init__.py
fair/templates/config.jinja
fair/templates/hist.jinja
fair/testing.py
fair/user_config/__init__.py
fair/user_config/globbing.py
fair/user_config/validation.py
fair/utilities.py
fair/virtualenv.py
fair_cli-0.9.8.dist-info/LICENSE
fair_cli-0.9.8.dist-info/METADATA
fair_cli-0.9.8.dist-info/WHEEL
fair_cli-0.9.8.dist-info/entry_points.txt
fair_cli-0.9.8.dist-info/RECORD
