Metadata-Version: 2.3
Name: fair-cli
Version: 0.9.8
Summary: Synchronization interface for the SCRC FAIR Data Pipeline registry
License: BSD-2-Clause
Keywords: FAIR Data Pipeline,FAIR,Data Management,Provenance
Author: Richard Reeve
Author-email: richard.reeve@glasgow.ac.uk
Requires-Python: >=3.9.0,<4.0.0
Classifier: Development Status :: 4 - Beta
Classifier: Environment :: Console
Classifier: Intended Audience :: Science/Research
Classifier: License :: OSI Approved :: BSD License
Classifier: Operating System :: MacOS
Classifier: Operating System :: OS Independent
Classifier: Operating System :: POSIX :: Linux
Classifier: Programming Language :: Python :: 3
Classifier: Programming Language :: Python :: 3.9
Classifier: Programming Language :: Python :: 3.10
Classifier: Programming Language :: Python :: 3.11
Classifier: Programming Language :: Python :: 3.12
Classifier: Programming Language :: Python :: 3.13
Classifier: Topic :: Database :: Front-Ends
Classifier: Topic :: Scientific/Engineering
Provides-Extra: all
Requires-Dist: GitPython (>=3.1.18,<4.0.0)
Requires-Dist: Jinja2 (>=3.0.1,<4.0.0)
Requires-Dist: PyYAML (>=5.4.1,<7.0.0)
Requires-Dist: click (>=8.0.0,<9.0.0)
Requires-Dist: email-validator (>=1.1.3,<2.0.0)
Requires-Dist: fake-useragent (>=1,<2)
Requires-Dist: pre-commit (>=3,<4)
Requires-Dist: pydantic[email] (>=1.9.0,<2.0.0)
Requires-Dist: requests (>=2.23.0,<3.0.0)
Requires-Dist: rich (>=10.2.3,<12.0.0)
Requires-Dist: semver (>=2.13.0,<3.0.0)
Requires-Dist: simplejson (>=3.17.5,<4.0.0)
Requires-Dist: toml (>=0.10.2,<0.11.0)
Requires-Dist: validators (>=0.18.2,<0.19.0)
Project-URL: Documentation, https://www.fairdatapipeline.org/docs/interface/fdp/
Project-URL: Homepage, https://www.fairdatapipeline.org/
Project-URL: Issue Tracker, https://github.com/FAIRDataPipeline/FAIR-CLI/issues
Project-URL: Repository, https://github.com/FAIRDataPipeline/FAIR-CLI
